TeleLite/__init__.py
TeleLite/bot.py
TeleLite/utils.py
telelite-0.1.2.dist-info/METADATA
telelite-0.1.2.dist-info/WHEEL
telelite-0.1.2.dist-info/top_level.txt
telelite-0.1.2.dist-info/RECORD
