Metadata-Version: 2.4
Name: telelite
Version: 0.1.2
Summary: Lightweight Telegram Bot Library
Author: YourName
Requires-Python: >=3.7
Requires-Dist: Flask>=2.2.5
Requires-Dist: aiohttp>=3.8.4
Requires-Dist: requests>=2.31.0
Dynamic: author
Dynamic: requires-dist
Dynamic: requires-python
Dynamic: summary
